dqueue/__init__.py
dqueue/api.py
dqueue/app.py
dqueue/auth.py
dqueue/cli.py
dqueue/client.py
dqueue/core.py
dqueue/data.py
dqueue/database.py
dqueue/dqtyping.py
dqueue/entry.py
dqueue/extralogging.py
dqueue/proxy.py
dqueue/stats.py
dqueue/tools.py
oda_node-0.1.55.dist-info/COPYING
oda_node-0.1.55.dist-info/METADATA
oda_node-0.1.55.dist-info/WHEEL
oda_node-0.1.55.dist-info/entry_points.txt
oda_node-0.1.55.dist-info/top_level.txt
oda_node-0.1.55.dist-info/RECORD
