Metadata-Version: 2.1
Name: oda-node
Version: 0.1.55
Summary: a queue manager (yet another)
Home-page: https://odahub.io/
Author: Volodymyr Savchenko
Author-email: vladimir.savchenko@gmail.com
License: MIT
Platform: UNKNOWN
Classifier: Development Status :: 4 - Beta
Classifier: Environment :: Console
Classifier: Intended Audience :: Science/Research
Classifier: License :: OSI Approved :: GNU General Public License v2 or later (GPLv2+)
Classifier: Operating System :: POSIX
Classifier: Programming Language :: Python :: 2.7
Classifier: Programming Language :: Python :: 3.4
Classifier: Programming Language :: Python :: 3.5
Classifier: Programming Language :: Python :: 3.6
Classifier: Programming Language :: Python :: 3.7
Classifier: Topic :: Internet
Classifier: Topic :: Scientific/Engineering
Requires-Dist: marshmallow
Requires-Dist: apispec
Requires-Dist: flasgger
Requires-Dist: bravado
Requires-Dist: termcolor
Requires-Dist: pymysql
Requires-Dist: peewee
Requires-Dist: retrying
Requires-Dist: oda-knowledge-base[cwl] (>=0.7.0)
Requires-Dist: pyjwt
Requires-Dist: pylogstash-context
